pyustc/__init__.py
pyustc/_singleton.py
pyustc/_url.py
pyustc/cas/__init__.py
pyustc/cas/client.py
pyustc/cas/info.py
pyustc/eams/__init__.py
pyustc/eams/_course.py
pyustc/eams/_grade.py
pyustc/eams/adjust.py
pyustc/eams/client.py
pyustc/eams/select.py
pyustc/young/__init__.py
pyustc/young/_user.py
pyustc/young/filter.py
pyustc/young/second_class.py
pyustc/young/service.py
pyustc-1.1.1.dist-info/licenses/LICENSE
pyustc-1.1.1.dist-info/WHEEL
pyustc-1.1.1.dist-info/METADATA
pyustc-1.1.1.dist-info/RECORD
