Metadata-Version: 2.4
Name: pyustc
Version: 1.1.1
Summary: A Python package that allows for quick use of USTC network services
Author: XeF2
Author-email: XeF2 <contact@xef2.top>
License-Expression: MIT
License-File: LICENSE
Classifier: Development Status :: 5 - Production/Stable
Classifier: Operating System :: OS Independent
Classifier: Programming Language :: Python :: 3.13
Classifier: Topic :: Software Development :: Libraries :: Python Modules
Requires-Dist: fake-useragent>=2.2.0,<3
Requires-Dist: httpx>=0.28.1,<0.29
Requires-Dist: pycryptodome>=3.23.0,<4
Requires-Python: >=3.11
Project-URL: Homepage, https://github.com/USTC-XeF2/pyustc
Project-URL: Issues, https://github.com/USTC-XeF2/pyustc/issues
